{
  "id": "1cf78c13-67b0-4b52-bc35-2fc8c6aea854",
  "prevId": "c489f023-b1b7-4ac7-854c-21e5669d6512",
  "version": "7",
  "dialect": "postgresql",
  "tables": {
    "public.words": {
      "name": "words",
      "schema": "",
      "columns": {
        "id": {
          "name": "id",
          "type": "serial",
          "primaryKey": true,
          "notNull": true
        },
        "word": {
          "name": "word",
          "type": "text",
          "primaryKey": false,
          "notNull": true
        },
        "translation": {
          "name": "translation",
          "type": "text",
          "primaryKey": false,
          "notNull": true
        },
        "example": {
          "name": "example",
          "type": "text",
          "primaryKey": false,
          "notNull": true
        },
        "score": {
          "name": "score",
          "type": "integer",
          "primaryKey": false,
          "notNull": false,
          "default": 0
        }
      },
      "indexes": {},
      "foreignKeys": {},
      "compositePrimaryKeys": {},
      "uniqueConstraints": {}
    }
  },
  "enums": {},
  "schemas": {},
  "_meta": {
    "columns": {},
    "schemas": {},
    "tables": {}
  }
}
